afat/__init__.py
afat/admin.py
afat/app_settings.py
afat/apps.py
afat/auth_hooks.py
afat/constants.py
afat/forms.py
afat/managers.py
afat/providers.py
afat/tasks.py
afat/utils.py
afat/handler/esi_handler.py
afat/helper/__init__.py
afat/helper/association.py
afat/helper/fatlinks.py
afat/helper/time.py
afat/helper/users.py
afat/helper/views.py
afat/locale/.gitkeep
afat/locale/django.pot
afat/locale/cs_CZ/LC_MESSAGES/django.mo
afat/locale/cs_CZ/LC_MESSAGES/django.po
afat/locale/de/LC_MESSAGES/.gitkeep
afat/locale/de/LC_MESSAGES/django.mo
afat/locale/de/LC_MESSAGES/django.po
afat/locale/es/LC_MESSAGES/.gitkeep
afat/locale/es/LC_MESSAGES/django.mo
afat/locale/es/LC_MESSAGES/django.po
afat/locale/fr_FR/LC_MESSAGES/.gitkeep
afat/locale/fr_FR/LC_MESSAGES/django.mo
afat/locale/fr_FR/LC_MESSAGES/django.po
afat/locale/it_IT/LC_MESSAGES/.gitkeep
afat/locale/it_IT/LC_MESSAGES/django.mo
afat/locale/it_IT/LC_MESSAGES/django.po
afat/locale/ja/LC_MESSAGES/.gitkeep
afat/locale/ja/LC_MESSAGES/django.mo
afat/locale/ja/LC_MESSAGES/django.po
afat/locale/ko_KR/LC_MESSAGES/.gitkeep
afat/locale/ko_KR/LC_MESSAGES/django.mo
afat/locale/ko_KR/LC_MESSAGES/django.po
afat/locale/nl_NL/LC_MESSAGES/django.mo
afat/locale/nl_NL/LC_MESSAGES/django.po
afat/locale/pl_PL/LC_MESSAGES/django.mo
afat/locale/pl_PL/LC_MESSAGES/django.po
afat/locale/ru/LC_MESSAGES/.gitkeep
afat/locale/ru/LC_MESSAGES/django.mo
afat/locale/ru/LC_MESSAGES/django.po
afat/locale/sk/LC_MESSAGES/django.mo
afat/locale/sk/LC_MESSAGES/django.po
afat/locale/uk/LC_MESSAGES/django.mo
afat/locale/uk/LC_MESSAGES/django.po
afat/locale/zh_Hans/LC_MESSAGES/.gitkeep
afat/locale/zh_Hans/LC_MESSAGES/django.mo
afat/locale/zh_Hans/LC_MESSAGES/django.po
afat/management/commands/afat_import_from_allianceauth_fat.py
afat/management/commands/afat_load_shiptypes.py
afat/management/commands/afat_migrate_affiliation_history.py
afat/management/commands/afat_migrate_fleet_types.py
afat/migrations/0001_initial.py
afat/migrations/0002_manualfat.py
allianceauth_afat-4.3.2.dist-info/METADATA
allianceauth_afat-4.3.2.dist-info/WHEEL
allianceauth_afat-4.3.2.dist-info/licenses/LICENSE
allianceauth_afat-4.3.2.dist-info/RECORD
