Metadata-Version: 2.4
Name: allianceauth-afat
Version: 4.3.2
Summary: Another Fleet Activity Tracking tool for Alliance Auth
Project-URL: Changelog, https://github.com/ppfeufer/allianceauth-afat/blob/master/CHANGELOG.md
Project-URL: Codecov, https://codecov.io/gh/ppfeufer/allianceauth-afat
Project-URL: Discord, https://discord.gg/fjnHAmk
Project-URL: Documentation, https://github.com/ppfeufer/allianceauth-afat/blob/master/README.md
Project-URL: Donation, https://ko-fi.com/ppfeufer
Project-URL: GitHub, https://github.com/ppfeufer/allianceauth-afat
Project-URL: Tracker, https://github.com/ppfeufer/allianceauth-afat/issues
Project-URL: Translation, https://weblate.ppfeufer.de/projects/alliance-auth-apps/allianceauth-afat/
Author-email: Peter Pfeufer <develop@ppfeufer.de>
License:                     GNU GENERAL PUBLIC LICENSE
License-File: LICENSE
Keywords: allianceauth,eveonline,fleet,fleet-activity,fleet-tracking,tracking
Classifier: Environment :: Web Environment
Classifier: Framework :: Django
Classifier: Framework :: Django :: 4.2
Classifier: Intended Audience :: Developers
Classifier: License :: OSI Approved :: GNU General Public License v3 (GPLv3)
Classifier: Operating System :: OS Independent
Classifier: Programming Language :: Python
Classifier: Programming Language :: Python :: 3 :: Only
Classifier: Programming Language :: Python :: 3.10
Classifier: Programming Language :: Python :: 3.11
Classifier: Programming Language :: Python :: 3.12
Classifier: Programming Language :: Python :: 3.13
Classifier: Topic :: Internet :: WWW/HTTP
Classifier: Topic :: Internet :: WWW/HTTP :: Dynamic Content
Requires-Python: <3.14,>=3.10
Requires-Dist: allianceauth<5,>=4.12
Requires-Dist: django-esi<9,>=8
Requires-Dist: django-eveuniverse>=1.5.7
Requires-Dist: unidecode>=1.3.4
Provides-Extra: tests-allianceauth-latest
Requires-Dist: allianceauth-securegroups; extra == 'tests-allianceauth-latest'
Requires-Dist: coverage; extra == 'tests-allianceauth-latest'
Requires-Dist: django-webtest; extra == 'tests-allianceauth-latest'
Requires-Dist: fittings; extra == 'tests-allianceauth-latest'
